LICENCE
README.md
setup.py
polar_codes_py_uerj/GeraIndexRETRO.py
polar_codes_py_uerj/MatrizGeradora.py
polar_codes_py_uerj/__init__.py
polar_codes_py_uerj/auxCol.py
polar_codes_py_uerj/calculaLLR.py
polar_codes_py_uerj/calculaRETRO.py
polar_codes_py_uerj/codificador.py
polar_codes_py_uerj/convertobin.py
polar_codes_py_uerj/convertobininv.py
polar_codes_py_uerj/decodificador.py
polar_codes_py_uerj/fbitreversed.py
polar_codes_py_uerj/funcao_F.py
polar_codes_py_uerj/funcao_G.py
polar_codes_py_uerj/logF.py
polar_codes_py_uerj/montaMapa.py
polar_codes_py_uerj/performance_PC.py
polar_codes_py_uerj/polarizacao.py
polar_codes_py_uerj.egg-info/PKG-INFO
polar_codes_py_uerj.egg-info/SOURCES.txt
polar_codes_py_uerj.egg-info/dependency_links.txt
polar_codes_py_uerj.egg-info/requires.txt
polar_codes_py_uerj.egg-info/top_level.txt