Metadata-Version: 2.1
Name: polar-codes-py-uerj
Version: 1.0.0
Summary: Wrapper para codificação e decodificação utilizando Polar Codes
Author: Luiz Fernando Rangel
Author-email: lfsvrangel@gmail.com
License: MIT License
Keywords: polar codes
License-File: LICENCE
